[
  {
    "file": "assets/images/cabin/01.jpg",
    "caption": "Living room image 1",
    "aspectRatio": 1.7767653758542141
  },
  {
    "file": "assets/images/cabin/02.jpg",
    "caption": "Living room image 2",
    "aspectRatio": 1.7767653758542141
  },
  {
    "file": "assets/images/cabin/03.jpg",
    "caption": "Living room image 3",
    "aspectRatio": 1.7767653758542141
  },
  {
    "file": "assets/images/cabin/04.jpg",
    "caption": "Living room image 4",
    "aspectRatio": 1.7767653758542141
  },
  {
    "file": "assets/images/cabin/05.jpg",
    "caption": "Living room image 5",
    "aspectRatio": 1.7767653758542141
  },
  {
    "file": "assets/images/cabin/06.jpg",
    "caption": "Living room image 6",
    "aspectRatio": 1.7767653758542141
  },
  {
    "file": "assets/images/cabin/07.jpg",
    "caption": "Living room image 7",
    "aspectRatio": 1.7767653758542141
  },
  {
    "file": "assets/images/cabin/08.jpg",
    "caption": "Living room image 8",
    "aspectRatio": 1.7767653758542141
  },
  {
    "file": "assets/images/cabin/09.jpg",
    "caption": "Full kitchen image 1",
    "aspectRatio": 1.7767653758542141
  },
  {
    "file": "assets/images/cabin/10.jpg",
    "caption": "Full kitchen image 2",
    "aspectRatio": 1.7767653758542141
  },
  {
    "file": "assets/images/cabin/11.jpg",
    "caption": "Full kitchen image 3",
    "aspectRatio": 1.7777134587554269
  },
  {
    "file": "assets/images/cabin/12.jpg",
    "caption": "Full kitchen image 4",
    "aspectRatio": 1.7767653758542141
  },
  {
    "file": "assets/images/cabin/13.jpg",
    "caption": "Full kitchen image 5",
    "aspectRatio": 1.7767653758542141
  },
  {
    "file": "assets/images/cabin/14.jpg",
    "caption": "Full kitchen image 6",
    "aspectRatio": 1.7767653758542141
  },
  {
    "file": "assets/images/cabin/15.jpg",
    "caption": "Full kitchen image 7",
    "aspectRatio": 0.5628205128205128
  },
  {
    "file": "assets/images/cabin/16.jpg",
    "caption": "Bedroom image 1",
    "aspectRatio": 1.7767653758542141
  },
  {
    "file": "assets/images/cabin/17.jpg",
    "caption": "Bedroom image 2",
    "aspectRatio": 1.7767653758542141
  },
  {
    "file": "assets/images/cabin/18.jpg",
    "caption": "Bedroom image 3",
    "aspectRatio": 1.7767653758542141
  },
  {
    "file": "assets/images/cabin/19.jpg",
    "caption": "Full bathroom image 1",
    "aspectRatio": 1.7767653758542141
  },
  {
    "file": "assets/images/cabin/20.jpg",
    "caption": "Full bathroom image 2",
    "aspectRatio": 0.5628205128205128
  },
  {
    "file": "assets/images/cabin/21.jpg",
    "caption": "Full bathroom image 3",
    "aspectRatio": 0.5628205128205128
  },
  {
    "file": "assets/images/cabin/22.jpg",
    "caption": "Full bathroom image 4",
    "aspectRatio": 1.7777117384843981
  },
  {
    "file": "assets/images/cabin/23.jpg",
    "caption": "Full bathroom image 5",
    "aspectRatio": 1.777810915597972
  },
  {
    "file": "assets/images/cabin/24.jpg",
    "caption": "Laundry area image 1",
    "aspectRatio": 1.7767653758542141
  },
  {
    "file": "assets/images/cabin/25.jpg",
    "caption": "Exterior image 1",
    "aspectRatio": 1.7767653758542141
  },
  {
    "file": "assets/images/cabin/26.jpg",
    "caption": "Exterior image 2",
    "aspectRatio": 1.7767653758542141
  },
  {
    "file": "assets/images/cabin/27.jpg",
    "caption": "Exterior image 3",
    "aspectRatio": 1.7778102189781022
  },
  {
    "file": "assets/images/cabin/28.jpg",
    "caption": "Exterior image 4",
    "aspectRatio": 1.7767653758542141
  },
  {
    "file": "assets/images/cabin/29.jpg",
    "caption": "Exterior image 5",
    "aspectRatio": 1.7767653758542141
  },
  {
    "file": "assets/images/cabin/30.jpg",
    "caption": "Exterior image 6",
    "aspectRatio": 1.7767653758542141
  },
  {
    "file": "assets/images/cabin/31.jpg",
    "caption": "Exterior image 7",
    "aspectRatio": 1.7767653758542141
  },
  {
    "file": "assets/images/cabin/32.jpg",
    "caption": "Exterior image 8",
    "aspectRatio": 1.777810650887574
  },
  {
    "file": "assets/images/cabin/33.jpg",
    "caption": "Exterior image 9",
    "aspectRatio": 1.7767653758542141
  },
  {
    "file": "assets/images/cabin/34.jpg",
    "caption": "Hot tub image 1",
    "aspectRatio": 1.7767653758542141
  },
  {
    "file": "assets/images/cabin/35.jpg",
    "caption": "Hot tub image 2",
    "aspectRatio": 1.7767653758542141
  },
  {
    "file": "assets/images/cabin/36.jpg",
    "caption": "Hot tub image 3",
    "aspectRatio": 1.7767653758542141
  }
]